<?xml version="1.0" encoding="UTF-8"?>
<result xmlns="https://production.bbc.co.uk/isite2/contentreader/xml/result"><metadata><modifiedDateTime>2016-02-26T01:31:27.146812Z</modifiedDateTime><creationDateTime>2016-02-26T01:31:27.146812Z</creationDateTime><type>deck</type><fileId>zgc6cwx</fileId><guid>389ebce0-a44f-4f93-b055-ddc44b542816</guid></metadata><document><deck xmlns="https://production.bbc.co.uk/isite2/project/education/deck">
                    <information>
                        <id>zgc6cwx</id>
                        <isite-title>Alkanes and alkenes - CCEA</isite-title>
                    </information>
                    <start-bookend>
                        <start-bookend-image-pid/>
                    </start-bookend>
                    <cards>
                        <card>
                    <card-id><result xmlns="https://production.bbc.co.uk/isite2/contentreader/xml/result"><metadata><modifiedDateTime>2016-02-26T01:31:27.146812Z</modifiedDateTime><creationDateTime>2016-02-26T01:31:27.146812Z</creationDateTime><type>card</type><fileId>zxt4tyc</fileId><guid>37741a30-ecd7-444d-8375-ec8af6e3c038</guid></metadata><document><card xmlns="https://production.bbc.co.uk/isite2/project/education/card">
                    <basic-information>
                        <id>zxt4tyc</id>
                        <isite-title>Alkanes - CCEA</isite-title>
                        <type>summary</type>
                        <headline>Alkanes</headline>
                        <body-text><result xmlns="https://production.bbc.co.uk/isite2/contentreader/xml/result"><metadata><modifiedDateTime>2016-02-26T01:31:27.146812Z</modifiedDateTime><creationDateTime>2016-02-26T01:31:27.146812Z</creationDateTime><type>card-formatted-text</type><fileId>zckpk7h</fileId><guid>01b6b7ee-b38f-4d45-b9ef-86935b9ea78e</guid></metadata><document><card-formatted-text xmlns="https://production.bbc.co.uk/isite2/project/education/card-formatted-text">
  <id label="zckpk7h">zckpk7h</id>
    <text>
<p><strong>Alkanes</strong> are hydrocarbons, compounds of hydrogen and carbon only</p>
<p>The alkanes form an <strong>homologous series</strong> with the general formula C<sub>n</sub>H<sub>2n+2</sub>, eg methane CH<sub>4</sub>, ethane C<sub>2</sub>H<sub>6</sub></p>
<p>Alkanes molecules only contain C–C and C–H single bonds</p>
<p>Alkanes are saturated molecules because they do not contain C=C double bonds</p>
<p>Alkanes do not decolourise orange bromine water</p>
</text>	
</card-formatted-text></document></result></body-text>
                    </basic-information>
                    <audio>
                        <audio-pid/>
                        <audio-text/>
                    </audio>
                    <quiz>
                        <qid/>
                        <quiz-image/>
                    </quiz>
                    <glossary-term>
                        <glossary/>
                        <glossary-front-image/>
                        <glossary-back-image/>
                    </glossary-term>
                    <infographic>
                        <infographic-front-image/>
                        <infographic-front-headline/>
                        <infographic-back-image/>
                        <infographic-back-headline/>
                    </infographic>
                    <quote>
                        <quote-text/>
                        <quote-author/>
                        <quote-author-information/>
                    </quote>
                    <video>
                        <video-pid/>
                        <video-text/>
                    </video>
                </card></document></result></card-id>
                </card><card>
                    <card-id><result xmlns="https://production.bbc.co.uk/isite2/contentreader/xml/result"><metadata><modifiedDateTime>2016-02-26T01:31:27.146812Z</modifiedDateTime><creationDateTime>2016-02-26T01:31:27.146812Z</creationDateTime><type>card</type><fileId>zgywfrd</fileId><guid>ac9c521e-9fbc-4f4d-927d-a5c3569b7fcc</guid></metadata><document><card xmlns="https://production.bbc.co.uk/isite2/project/education/card">
                    <basic-information>
                        <id>zgywfrd</id>
                        <isite-title>Alkane</isite-title>
                        <type>glossary</type>
                        <headline/>
                        <body-text/>
                    </basic-information>
                    <audio>
                        <audio-pid/>
                        <audio-text/>
                    </audio>
                    <quiz>
                        <qid/>
                        <quiz-image/>
                    </quiz>
                    <glossary-term>
                        <glossary><result xmlns="https://production.bbc.co.uk/isite2/contentreader/xml/result"><metadata><modifiedDateTime>2014-06-26T15:35:41.932808Z</modifiedDateTime><creationDateTime>2014-06-26T15:35:41.932808Z</creationDateTime><type>sg-glossary-term</type><fileId>zwjs9j6</fileId><guid>79fbedca-2556-4fdc-b304-8313f10e0963</guid></metadata><document><glossary-term xmlns="https://production.bbc.co.uk/isite2/project/education/sg-glossary-term">
                    <id label="zwjs9j6">zwjs9j6</id>
                    <term>alkane</term>
                    <description>Saturated hydrocarbon. A compound of hydrogen and carbon only, with no C=C bonds.</description>
                    <language>English</language>
                </glossary-term></document></result></glossary>
                        <glossary-front-image/>
                        <glossary-back-image/>
                    </glossary-term>
                    <infographic>
                        <infographic-front-image/>
                        <infographic-front-headline/>
                        <infographic-back-image/>
                        <infographic-back-headline/>
                    </infographic>
                    <quote>
                        <quote-text/>
                        <quote-author/>
                        <quote-author-information/>
                    </quote>
                    <video>
                        <video-pid/>
                        <video-text/>
                    </video>
                </card></document></result></card-id>
                </card><card>
                    <card-id><result xmlns="https://production.bbc.co.uk/isite2/contentreader/xml/result"><metadata><modifiedDateTime>2016-02-26T01:31:27.146812Z</modifiedDateTime><creationDateTime>2016-02-26T01:31:27.146812Z</creationDateTime><type>card</type><fileId>z2qyj6f</fileId><guid>b386e962-d325-478c-8ba9-54d18a6a8d6b</guid></metadata><document><card xmlns="https://production.bbc.co.uk/isite2/project/education/card">
                    <basic-information>
                        <id>z2qyj6f</id>
                        <isite-title>Label which bromine water test tube contains an alkane</isite-title>
                        <type>infographic</type>
                        <headline/>
                        <body-text/>
                    </basic-information>
                    <audio>
                        <audio-pid/>
                        <audio-text/>
                    </audio>
                    <quiz>
                        <qid/>
                        <quiz-image/>
                    </quiz>
                    <glossary-term>
                        <glossary/>
                        <glossary-front-image/>
                        <glossary-back-image/>
                    </glossary-term>
                    <infographic>
                        <infographic-front-image>zs8pcwx</infographic-front-image>
                        <infographic-front-headline>Label which bromine water test tube contains an alkane </infographic-front-headline>
                        <infographic-back-image>zc6r7hv</infographic-back-image>
                        <infographic-back-headline>Bromine water is decolourised by alkenes but not by alkanes</infographic-back-headline>
                    </infographic>
                    <quote>
                        <quote-text/>
                        <quote-author/>
                        <quote-author-information/>
                    </quote>
                    <video>
                        <video-pid/>
                        <video-text/>
                    </video>
                </card></document></result></card-id>
                </card><card>
                    <card-id><result xmlns="https://production.bbc.co.uk/isite2/contentreader/xml/result"><metadata><modifiedDateTime>2016-02-26T01:31:27.146812Z</modifiedDateTime><creationDateTime>2016-02-26T01:31:27.146812Z</creationDateTime><type>card</type><fileId>zwpkp39</fileId><guid>3492b9c0-20be-4c1b-af8c-1d8ba44179bd</guid></metadata><document><card xmlns="https://production.bbc.co.uk/isite2/project/education/card">
                    <basic-information>
                        <id>zwpkp39</id>
                        <isite-title>Homologous series</isite-title>
                        <type>glossary</type>
                        <headline/>
                        <body-text/>
                    </basic-information>
                    <audio>
                        <audio-pid/>
                        <audio-text/>
                    </audio>
                    <quiz>
                        <qid/>
                        <quiz-image/>
                    </quiz>
                    <glossary-term>
                        <glossary><result xmlns="https://production.bbc.co.uk/isite2/contentreader/xml/result"><metadata><modifiedDateTime>2014-06-26T15:45:13.344762Z</modifiedDateTime><creationDateTime>2014-06-26T15:45:13.344762Z</creationDateTime><type>sg-glossary-term</type><fileId>ztg2yrd</fileId><guid>f5046a93-6c5b-4af5-a312-4e5daa8fbbcb</guid></metadata><document><glossary-term xmlns="https://production.bbc.co.uk/isite2/project/education/sg-glossary-term">
                    <id label="ztg2yrd">ztg2yrd</id>
                    <term>homologous series</term>
                    <description>A 'family' of organic compounds that have the same functional group and similar chemical properties. </description>
                    <language>English</language>
                </glossary-term></document></result></glossary>
                        <glossary-front-image/>
                        <glossary-back-image/>
                    </glossary-term>
                    <infographic>
                        <infographic-front-image/>
                        <infographic-front-headline/>
                        <infographic-back-image/>
                        <infographic-back-headline/>
                    </infographic>
                    <quote>
                        <quote-text/>
                        <quote-author/>
                        <quote-author-information/>
                    </quote>
                    <video>
                        <video-pid/>
                        <video-text/>
                    </video>
                </card></document></result></card-id>
                </card><card>
                    <card-id><result xmlns="https://production.bbc.co.uk/isite2/contentreader/xml/result"><metadata><modifiedDateTime>2016-02-26T01:31:27.146812Z</modifiedDateTime><creationDateTime>2016-02-26T01:31:27.146812Z</creationDateTime><type>card</type><fileId>zpxgmnb</fileId><guid>d73493b4-9ade-4c97-a3cd-437a3425f28d</guid></metadata><document><card xmlns="https://production.bbc.co.uk/isite2/project/education/card">
                    <basic-information>
                        <id>zpxgmnb</id>
                        <isite-title>What is the formula for the alkane butane?</isite-title>
                        <type>infographic</type>
                        <headline/>
                        <body-text/>
                    </basic-information>
                    <audio>
                        <audio-pid/>
                        <audio-text/>
                    </audio>
                    <quiz>
                        <qid/>
                        <quiz-image/>
                    </quiz>
                    <glossary-term>
                        <glossary/>
                        <glossary-front-image/>
                        <glossary-back-image/>
                    </glossary-term>
                    <infographic>
                        <infographic-front-image>zsydnbk</infographic-front-image>
                        <infographic-front-headline>What is the formula for the alkane butane?</infographic-front-headline>
                        <infographic-back-image>z8wnk7h</infographic-back-image>
                        <infographic-back-headline/>
                    </infographic>
                    <quote>
                        <quote-text/>
                        <quote-author/>
                        <quote-author-information/>
                    </quote>
                    <video>
                        <video-pid/>
                        <video-text/>
                    </video>
                </card></document></result></card-id>
                </card><card>
                    <card-id><result xmlns="https://production.bbc.co.uk/isite2/contentreader/xml/result"><metadata><modifiedDateTime>2016-02-26T01:31:27.146812Z</modifiedDateTime><creationDateTime>2016-02-26T01:31:27.146812Z</creationDateTime><type>card</type><fileId>zy6rxsg</fileId><guid>e92f6bc7-067b-4d69-a3bd-c2b6a9f97080</guid></metadata><document><card xmlns="https://production.bbc.co.uk/isite2/project/education/card">
                    <basic-information>
                        <id>zy6rxsg</id>
                        <isite-title>Combustion</isite-title>
                        <type>summary</type>
                        <headline>Combustion</headline>
                        <body-text><result xmlns="https://production.bbc.co.uk/isite2/contentreader/xml/result"><metadata><modifiedDateTime>2016-02-26T01:31:27.146812Z</modifiedDateTime><creationDateTime>2016-02-26T01:31:27.146812Z</creationDateTime><type>card-formatted-text</type><fileId>zgs8nbk</fileId><guid>c7892c3f-708f-4b8f-9d69-3b2699003604</guid></metadata><document><card-formatted-text xmlns="https://production.bbc.co.uk/isite2/project/education/card-formatted-text">
  <id label="zgs8nbk">zgs8nbk</id>
    <text>
<p>Alkanes undergo complete combustion in a good supply of oxygen, producing carbon dioxide and water, eg <em>CH<sub>4</sub> + 2O<sub>2</sub> → CO<sub>2</sub> + 2H<sub>2</sub>O</em></p>
<p>When there is insufficient oxygen, incomplete combustion occurs</p>
<p>Incomplete combustion of a hydrocarbon fuel releases less energy, and it produces water, carbon monoxide and soot</p>
<p>Carbon monoxide is a toxic gas whilst soot blackens buildings</p>
</text>	
</card-formatted-text></document></result></body-text>
                    </basic-information>
                    <audio>
                        <audio-pid/>
                        <audio-text/>
                    </audio>
                    <quiz>
                        <qid/>
                        <quiz-image/>
                    </quiz>
                    <glossary-term>
                        <glossary/>
                        <glossary-front-image/>
                        <glossary-back-image/>
                    </glossary-term>
                    <infographic>
                        <infographic-front-image/>
                        <infographic-front-headline/>
                        <infographic-back-image/>
                        <infographic-back-headline/>
                    </infographic>
                    <quote>
                        <quote-text/>
                        <quote-author/>
                        <quote-author-information/>
                    </quote>
                    <video>
                        <video-pid/>
                        <video-text/>
                    </video>
                </card></document></result></card-id>
                </card><card>
                    <card-id><result xmlns="https://production.bbc.co.uk/isite2/contentreader/xml/result"><metadata><modifiedDateTime>2016-02-26T01:31:27.146812Z</modifiedDateTime><creationDateTime>2016-02-26T01:31:27.146812Z</creationDateTime><type>card</type><fileId>ztyjycw</fileId><guid>979823ea-7bf0-4d41-b37e-4b43ac4a7330</guid></metadata><document><card xmlns="https://production.bbc.co.uk/isite2/project/education/card">
                    <basic-information>
                        <id>ztyjycw</id>
                        <isite-title>Alkenes - CCEA</isite-title>
                        <type>summary</type>
                        <headline>Alkenes</headline>
                        <body-text><result xmlns="https://production.bbc.co.uk/isite2/contentreader/xml/result"><metadata><modifiedDateTime>2016-02-26T01:31:27.146812Z</modifiedDateTime><creationDateTime>2016-02-26T01:31:27.146812Z</creationDateTime><type>card-formatted-text</type><fileId>zgdsdmn</fileId><guid>e46559b0-f357-48ad-9f22-6155d6f7bd35</guid></metadata><document><card-formatted-text xmlns="https://production.bbc.co.uk/isite2/project/education/card-formatted-text">
  <id label="zgdsdmn">zgdsdmn</id>
    <text>
<p><strong>Alkenes</strong> are hydrocarbons with the general formula C<sub>n</sub>H<sub>2n</sub>, eg ethene C<sub>2</sub>H<sub>4</sub>, propene C<sub>3</sub>H<sub>6</sub></p>
<p>Alkene molecules contain the <strong>functional group</strong> C=C (a carbon–carbon double bond), so they are <strong>unsaturated</strong></p>
<p>Alkenes decolourise orange bromine water because they contain C=C bonds</p>
<p>Alkenes react with substances like bromine and hydrogen in addition reactions, eg <em>C<sub>2</sub>H<sub>4</sub> + H<sub>2</sub> → C<sub>2</sub>H<sub>6</sub></em></p>
</text>	
</card-formatted-text></document></result></body-text>
                    </basic-information>
                    <audio>
                        <audio-pid/>
                        <audio-text/>
                    </audio>
                    <quiz>
                        <qid/>
                        <quiz-image/>
                    </quiz>
                    <glossary-term>
                        <glossary/>
                        <glossary-front-image/>
                        <glossary-back-image/>
                    </glossary-term>
                    <infographic>
                        <infographic-front-image/>
                        <infographic-front-headline/>
                        <infographic-back-image/>
                        <infographic-back-headline/>
                    </infographic>
                    <quote>
                        <quote-text/>
                        <quote-author/>
                        <quote-author-information/>
                    </quote>
                    <video>
                        <video-pid/>
                        <video-text/>
                    </video>
                </card></document></result></card-id>
                </card><card>
                    <card-id><result xmlns="https://production.bbc.co.uk/isite2/contentreader/xml/result"><metadata><modifiedDateTime>2016-02-26T01:31:27.146812Z</modifiedDateTime><creationDateTime>2016-02-26T01:31:27.146812Z</creationDateTime><type>card</type><fileId>z3s8nbk</fileId><guid>6252ccaf-5dd2-4102-b36e-face279753b9</guid></metadata><document><card xmlns="https://production.bbc.co.uk/isite2/project/education/card">
                    <basic-information>
                        <id>z3s8nbk</id>
                        <isite-title>Alkene</isite-title>
                        <type>glossary</type>
                        <headline/>
                        <body-text/>
                    </basic-information>
                    <audio>
                        <audio-pid/>
                        <audio-text/>
                    </audio>
                    <quiz>
                        <qid/>
                        <quiz-image/>
                    </quiz>
                    <glossary-term>
                        <glossary><result xmlns="https://production.bbc.co.uk/isite2/contentreader/xml/result"><metadata><modifiedDateTime>2014-06-26T15:30:19.900278Z</modifiedDateTime><creationDateTime>2014-06-26T15:30:19.900278Z</creationDateTime><type>sg-glossary-term</type><fileId>zhky9j6</fileId><guid>dfcc6b58-cf25-5748-8475-dbfdcbfac0f8</guid></metadata><document><glossary-term xmlns="https://production.bbc.co.uk/isite2/project/education/sg-glossary-term">
  <id label="zhky9j6">zhky9j6</id>
  <term>alkene</term>
  <description>Unsaturated hydrocarbon with a double bond between the carbon atoms.</description>
  <language>English</language>
</glossary-term></document></result></glossary>
                        <glossary-front-image/>
                        <glossary-back-image/>
                    </glossary-term>
                    <infographic>
                        <infographic-front-image/>
                        <infographic-front-headline/>
                        <infographic-back-image/>
                        <infographic-back-headline/>
                    </infographic>
                    <quote>
                        <quote-text/>
                        <quote-author/>
                        <quote-author-information/>
                    </quote>
                    <video>
                        <video-pid/>
                        <video-text/>
                    </video>
                </card></document></result></card-id>
                </card><card>
                    <card-id><result xmlns="https://production.bbc.co.uk/isite2/contentreader/xml/result"><metadata><modifiedDateTime>2016-02-26T01:31:27.146812Z</modifiedDateTime><creationDateTime>2016-02-26T01:31:27.146812Z</creationDateTime><type>card</type><fileId>zt6rxsg</fileId><guid>937806cf-be0c-4202-887f-72295de5bdf7</guid></metadata><document><card xmlns="https://production.bbc.co.uk/isite2/project/education/card">
                    <basic-information>
                        <id>zt6rxsg</id>
                        <isite-title>Alkenes have a carbon-carbon double bond</isite-title>
                        <type>infographic</type>
                        <headline/>
                        <body-text/>
                    </basic-information>
                    <audio>
                        <audio-pid/>
                        <audio-text/>
                    </audio>
                    <quiz>
                        <qid/>
                        <quiz-image/>
                    </quiz>
                    <glossary-term>
                        <glossary/>
                        <glossary-front-image/>
                        <glossary-back-image/>
                    </glossary-term>
                    <infographic>
                        <infographic-front-image>zw7ywxs</infographic-front-image>
                        <infographic-front-headline>Alkenes have a carbon-carbon double bond</infographic-front-headline>
                        <infographic-back-image/>
                        <infographic-back-headline/>
                    </infographic>
                    <quote>
                        <quote-text/>
                        <quote-author/>
                        <quote-author-information/>
                    </quote>
                    <video>
                        <video-pid/>
                        <video-text/>
                    </video>
                </card></document></result></card-id>
                </card><card>
                    <card-id><result xmlns="https://production.bbc.co.uk/isite2/contentreader/xml/result"><metadata><modifiedDateTime>2016-02-26T01:31:27.146812Z</modifiedDateTime><creationDateTime>2016-02-26T01:31:27.146812Z</creationDateTime><type>card</type><fileId>z3jyj6f</fileId><guid>5c94aa6f-8e0e-4a01-ab17-e3509d78d87f</guid></metadata><document><card xmlns="https://production.bbc.co.uk/isite2/project/education/card">
                    <basic-information>
                        <id>z3jyj6f</id>
                        <isite-title>Functional group</isite-title>
                        <type>glossary</type>
                        <headline/>
                        <body-text/>
                    </basic-information>
                    <audio>
                        <audio-pid/>
                        <audio-text/>
                    </audio>
                    <quiz>
                        <qid/>
                        <quiz-image/>
                    </quiz>
                    <glossary-term>
                        <glossary><result xmlns="https://production.bbc.co.uk/isite2/contentreader/xml/result"><metadata><modifiedDateTime>2014-06-26T15:45:13.344762Z</modifiedDateTime><creationDateTime>2014-06-26T15:45:13.344762Z</creationDateTime><type>sg-glossary-term</type><fileId>zt3qsbk</fileId><guid>6a47d9a6-8c0c-49bc-9937-0a95a9365940</guid></metadata><document><glossary-term xmlns="https://production.bbc.co.uk/isite2/project/education/sg-glossary-term">
                    <id label="zt3qsbk">zt3qsbk</id>
                    <term>functional group</term>
                    <description>An atom, or group of atoms, that determines the main chemical properties of an organic compound.</description>
                    <language>English</language>
                </glossary-term></document></result></glossary>
                        <glossary-front-image/>
                        <glossary-back-image/>
                    </glossary-term>
                    <infographic>
                        <infographic-front-image/>
                        <infographic-front-headline/>
                        <infographic-back-image/>
                        <infographic-back-headline/>
                    </infographic>
                    <quote>
                        <quote-text/>
                        <quote-author/>
                        <quote-author-information/>
                    </quote>
                    <video>
                        <video-pid/>
                        <video-text/>
                    </video>
                </card></document></result></card-id>
                </card><card>
                    <card-id><result xmlns="https://production.bbc.co.uk/isite2/contentreader/xml/result"><metadata><modifiedDateTime>2016-02-26T01:31:27.146812Z</modifiedDateTime><creationDateTime>2016-02-26T01:31:27.146812Z</creationDateTime><type>card</type><fileId>zxb2bk7</fileId><guid>9f3dff97-413e-433e-ae22-3339b4f5e750</guid></metadata><document><card xmlns="https://production.bbc.co.uk/isite2/project/education/card">
                    <basic-information>
                        <id>zxb2bk7</id>
                        <isite-title>Unsaturated</isite-title>
                        <type>glossary</type>
                        <headline/>
                        <body-text/>
                    </basic-information>
                    <audio>
                        <audio-pid/>
                        <audio-text/>
                    </audio>
                    <quiz>
                        <qid/>
                        <quiz-image/>
                    </quiz>
                    <glossary-term>
                        <glossary><result xmlns="https://production.bbc.co.uk/isite2/contentreader/xml/result"><metadata><modifiedDateTime>2014-06-26T15:30:19.900278Z</modifiedDateTime><creationDateTime>2014-06-26T15:30:19.900278Z</creationDateTime><type>sg-glossary-term</type><fileId>zbkrjxs</fileId><guid>afb3ae27-fbb2-5964-889d-a49edd015585</guid></metadata><document><glossary-term xmlns="https://production.bbc.co.uk/isite2/project/education/sg-glossary-term">
  <id label="zbkrjxs">zbkrjxs</id>
  <term>unsaturated</term>
  <description>An unsaturated compound contains at least one double or triple bond.</description>
  <language>English</language>
</glossary-term></document></result></glossary>
                        <glossary-front-image/>
                        <glossary-back-image/>
                    </glossary-term>
                    <infographic>
                        <infographic-front-image/>
                        <infographic-front-headline/>
                        <infographic-back-image/>
                        <infographic-back-headline/>
                    </infographic>
                    <quote>
                        <quote-text/>
                        <quote-author/>
                        <quote-author-information/>
                    </quote>
                    <video>
                        <video-pid/>
                        <video-text/>
                    </video>
                </card></document></result></card-id>
                </card><card>
                    <card-id><result xmlns="https://production.bbc.co.uk/isite2/contentreader/xml/result"><metadata><modifiedDateTime>2016-02-26T01:31:27.146812Z</modifiedDateTime><creationDateTime>2016-02-26T01:31:27.146812Z</creationDateTime><type>card</type><fileId>z2wsdmn</fileId><guid>c126e2a1-caa3-4b34-ab5a-73ed3b68c36d</guid></metadata><document><card xmlns="https://production.bbc.co.uk/isite2/project/education/card">
                    <basic-information>
                        <id>z2wsdmn</id>
                        <isite-title>Alkanes and alkenes</isite-title>
                        <type>quiz</type>
                        <headline>Alkanes and alkenes</headline>
                        <body-text/>
                    </basic-information>
                    <audio>
                        <audio-pid/>
                        <audio-text/>
                    </audio>
                    <quiz>
                        <qid>q588083618</qid>
                        <quiz-image/>
                    </quiz>
                    <glossary-term>
                        <glossary/>
                        <glossary-front-image/>
                        <glossary-back-image/>
                    </glossary-term>
                    <infographic>
                        <infographic-front-image/>
                        <infographic-front-headline/>
                        <infographic-back-image/>
                        <infographic-back-headline/>
                    </infographic>
                    <quote>
                        <quote-text/>
                        <quote-author/>
                        <quote-author-information/>
                    </quote>
                    <video>
                        <video-pid/>
                        <video-text/>
                    </video>
                </card></document></result></card-id>
                </card>
                    </cards>
                    <end-bookend>
                        <end-bookend-image-pid/>
                        <onward-journey/>
                    </end-bookend>
                </deck></document></result>